whisp/__init__.py
whisp/whisp_main.py
whisp/Whisper/__init__.py
whisp/Whisper/__main__.py
whisp/Whisper/audio.py
whisp/Whisper/decoding.py
whisp/Whisper/model.py
whisp/Whisper/tokenizer.py
whisp/Whisper/transcribe.py
whisp/Whisper/utils.py
whisp/Whisper/assets/__init__.py
whisp/Whisper/assets/mel_filters.npz
whisp/Whisper/assets/gpt2/merges.txt
whisp/Whisper/assets/gpt2/special_tokens_map.json
whisp/Whisper/assets/gpt2/tokenizer_config.json
whisp/Whisper/assets/gpt2/vocab.json
whisp/Whisper/assets/multilingual/added_tokens.json
whisp/Whisper/assets/multilingual/merges.txt
whisp/Whisper/assets/multilingual/special_tokens_map.json
whisp/Whisper/assets/multilingual/tokenizer_config.json
whisp/Whisper/assets/multilingual/vocab.json
whisp/Whisper/normalizers/__init__.py
whisp/Whisper/normalizers/basic.py
whisp/Whisper/normalizers/english.json
whisp/Whisper/normalizers/english.py
whisp-0.0.2.0.dist-info/METADATA
whisp-0.0.2.0.dist-info/WHEEL
whisp-0.0.2.0.dist-info/top_level.txt
whisp-0.0.2.0.dist-info/RECORD
