Metadata-Version: 2.1
Name: whisp
Version: 0.0.2.0
Summary: Whisper package
Author: Peteris N.
Requires-Dist: setuptools-rust
Requires-Dist: torch
Requires-Dist: transformers
Requires-Dist: ffmpeg-python
